[{"batch":"9","name":"강솔미","email":"rkdthfal132@gmail.com"},{"batch":"9","name":"고혁훈","email":"khh180cm@gmail.com"},{"batch":"9","name":"권오성","email":"monsterkos10@gmail.com"},{"batch":"9","name":"김대휘","email":"kdh92417@gmail.com"},{"batch":"9","name":"김동건","email":"dgk2481@gmail.com"},{"batch":"9","name":"김민지","email":"imjkim49@gmail.com"},{"batch":"9","name":"김정현","email":"junghyunhao@gmail.com "},{"batch":"9","name":"김지인","email":"Jeeinkim1219@gmail.com"},{"batch":"9","name":"김환일","email":"kpl5672@gmail.com"},{"batch":"9","name":"노광오","email":"shrhkddh0244@gmail.com"},{"batch":"9","name":"류제승","email":"crystalyst91@gmail.com"},{"batch":"9","name":"문성원","email":"swmarkmoon@gmail.com "},{"batch":"9","name":"박동경","email":"e1loldan@gmail.com"},{"batch":"9","name":"박상영","email":"pjkfckr@gmail.com"},{"batch":"9","name":"박준모","email":"junnoli18@gmail.com"},{"batch":"9","name":"박창수","email":"changsu5282@gmail.com"},{"batch":"9","name":"반현랑","email":"gusfkd2827@gmail.com"},{"batch":"9","name":"백용진","email":"yongineer1990@gmail.com"},{"batch":"9","name":"손혜인","email":"shl7683@gmail.com"},{"batch":"9","name":"송민규","email":"thdalsrb1111@gmail.com"},{"batch":"9","name":"양희연","email":"bmoyeon.d@gmail.com"},{"batch":"9","name":"윤빛나라","email":"yoonbitnara@gmail.com"},{"batch":"9","name":"이민서","email":"charleslee1222@gmail.com"},{"batch":"9","name":"이승민","email":"tkddn088@gmail.com"},{"batch":"9","name":"이유진","email":"yl540016@gmail.com"},{"batch":"9","name":"이재준","email":"gwejja@gmail.com"},{"batch":"9","name":"이종헌","email":"guitarlove00@gmail.com"},{"batch":"9","name":"이한별","email":"byeol4001@gmail.com"},{"batch":"9","name":"이호균","email":"hokyun.rhee@gmail.com"},{"batch":"9","name":"전성현","email":"4dallove@gmail.com"},{"batch":"9","name":"정나온","email":"naon.jeong@gmail.com"},{"batch":"9","name":"정수빈","email":"chlojeong@gmail.com"},{"batch":"9","name":"정수영","email":"aprilgreenery@gmail.com"},{"batch":"9","name":"정해빈","email":"jeonghb0212@gmail.com"},{"batch":"9","name":"진선경","email":"jinsk9268@gmail.com"},{"batch":"9","name":"최지원","email":"gwon9400@gmail.com"},{"batch":"9","name":"한국","email":"kxh72410@ucmo.edu"},{"batch":"9","name":"한수민","email":"tnals9323@gmail.com"},{"batch":"9","name":"한준수","email":"kljopuu@gmail.com"},{"batch":"9","name":"현정호","email":"offdutybyblo@gmail.com"},{"batch":"9","name":"홍정민","email":"azurestefan@gmail.com"},{"batch":"10","name":"권한성","email":"kyo3553@gmail.com"},{"batch":"10","name":"김경배","email":"rudqo14@gmail.com"},{"batch":"10","name":"김도환","email":"ehghksvjscl@gmail.com"},{"batch":"10","name":"김동현","email":"dongsagi90@gmail.com"},{"batch":"10","name":"김병준","email":"kbj7227@gmail.com"},{"batch":"10","name":"김신영","email":"bonbon0202@gmail.com"},{"batch":"10","name":"김효식","email":"luna23825@gmail.com"},{"batch":"10","name":"박민규","email":"kor0885@gmail.com"},{"batch":"10","name":"박예진","email":"yeajinpark91@gmail.com"},{"batch":"10","name":"배정규","email":"junggyoo.1@gmail.com"},{"batch":"10","name":"서동찬","email":"sdc337dc@gmail.com"},{"batch":"10","name":"손수정","email":"tnwjd060124@gmail.com"},{"batch":"10","name":"송수호","email":"ridou99@gmail.com"},{"batch":"10","name":"신영재","email":"syj9484@gmail.com"},{"batch":"10","name":"안솔","email":"sorry0194@gmail.com"},{"batch":"10","name":"오호근","email":"ghrms2525@gmail.com"},{"batch":"10","name":"윤지영","email":"ziyoung1121@gmail.com"},{"batch":"10","name":"이곤호","email":"sincerity410@gmail.com"},{"batch":"10","name":"이문영","email":"exid0429@gmail.com"},{"batch":"10","name":"이민호","email":"minho.lee0716@gmail.com"},{"batch":"10","name":"이병수","email":"djaxornwkd12@gmail.com"},{"batch":"10","name":"이병훈","email":"Bhooncoding@gmail.com"},{"batch":"10","name":"이상준","email":"0607juny@gmail.com"},{"batch":"10","name":"이윤식","email":"dark235612@gmail.com"},{"batch":"10","name":"이지윤","email":"i01029407043@gmail.com"},{"batch":"10","name":"이태성","email":"yotae07@gmail.com"},{"batch":"10","name":"이홍일","email":"dlghddlf1992@gmail.com"},{"batch":"10","name":"임현지","email":"imhyeonji0118@gmail.com"},{"batch":"10","name":"최운정","email":"charmingbbo@gmail.com"},{"batch":"10","name":"최준","email":"jun.choi.4928@gmail.com"},{"batch":"10","name":"최태희","email":"taehee.selena@gmail.com"},{"batch":"10","name":"황수미","email":"ifyouseeksoomi@gmail.com"},{"batch":"11","name":"강예지","email":"kyj07030911@gmail.com"},{"batch":"11","name":"고지원","email":"rhwldnjs1226@gmail.com"},{"batch":"11","name":"권창식","email":"Kcs15987@gmail.com"},{"batch":"11","name":"김건우","email":"gunoo0126@gmail.com"},{"batch":"11","name":"김규영","email":"apateonos@gmail.com"},{"batch":"11","name":"김기욱","email":"1218kim23@gmail.com"},{"batch":"11","name":"김동호","email":"zhappy114@gmail.com"},{"batch":"11","name":"김영지","email":"yjkim7257@gmail.com"},{"batch":"11","name":"김태수","email":"blakekim93@gmail.com"},{"batch":"11","name":"김태하","email":"taeha7b@gmail.com"},{"batch":"11","name":"김해준","email":"hj885353@gmail.com"},{"batch":"11","name":"김현우","email":"miretta20@gmail.com"},{"batch":"11","name":"류상욱","email":"ryuinkyoto@gmail.com"},{"batch":"11","name":"마상원","email":"ssamwonn@gmail.com"},{"batch":"11","name":"문태기","email":"orangemush99@gmail.com"},{"batch":"11","name":"박주엽","email":"wnduq8@gmail.com"},{"batch":"11","name":"박진아","email":"bluerose021318@gmail.com"},{"batch":"11","name":"손수민","email":"ssm2319@gmail.com"},{"batch":"11","name":"송다슬","email":"vates0328@gmail.com"},{"batch":"11","name":"오상구","email":"sangku824@gmail.com"},{"batch":"11","name":"오승하","email":"lilyoh628@gmail.com"},{"batch":"11","name":"왕민욱","email":"alsdnr4874@gmail.com"},{"batch":"11","name":"유휘찬","email":"dbgnlcks34@gmail.com"},{"batch":"11","name":"이건규","email":"hismayfly@gmail.com"},{"batch":"11","name":"이도윤","email":"doyoonleee@gmail.com"},{"batch":"11","name":"이상훈","email":"cloudlee711@gmail.com"},{"batch":"11","name":"이영섭","email":"dud8828@gmail.com"},{"batch":"11","name":"이용민","email":"eymin1259@gmail.com"},{"batch":"11","name":"이조은","email":"dlwhdms0326@gmail.com"},{"batch":"11","name":"이지연","email":"wldus9503@gmail.com"},{"batch":"11","name":"이충희","email":"choonghee.dev@gmail.com"},{"batch":"11","name":"이태현","email":"0417taehyun@gmail.com"},{"batch":"11","name":"이호현","email":"jyslshsgdy@gmail.com"},{"batch":"11","name":"이효정","email":"ovovv99@gmail.com"},{"batch":"11","name":"조윤민","email":"yoonminsohappy@gmail.com"},{"batch":"11","name":"조은별","email":"ebcebeb@gmail.com"},{"batch":"11","name":"최예흠","email":"coffee8357@gmail.com"},{"batch":"11","name":"한태규","email":"teagyu1058@gmail.com"},{"batch":"11","name":"황연욱","email":"younuk23@gmail.com"}]
